trm/__init__.py
trm/rmrlb.py
transactional_remove-1.0.9.dist-info/METADATA
transactional_remove-1.0.9.dist-info/WHEEL
transactional_remove-1.0.9.dist-info/entry_points.txt
transactional_remove-1.0.9.dist-info/top_level.txt
transactional_remove-1.0.9.dist-info/RECORD
